[
  {
    "date": "6/29/2019",
    "message_count": 25,
    "morning": "",
    "middle": "",
    "night": "",
    "high": "",
    "low": "",
    "pressure": "",
    "humidity": ""
  },
  {
    "date": "6/30/2019",
    "message_count": 115,
    "morning": "",
    "middle": "",
    "night": "",
    "high": "",
    "low": "",
    "pressure": "",
    "humidity": ""
  },
  {
    "date": "7/1/2019",
    "message_count": 364,
    "morning": "",
    "middle": "",
    "night": "",
    "high": "",
    "low": "",
    "pressure": "",
    "humidity": ""
  },
  {
    "date": "7/2/2019",
    "message_count": 182,
    "morning": "",
    "middle": "",
    "night": "",
    "high": "",
    "low": "",
    "pressure": "",
    "humidity": ""
  },
  {
    "date": "7/3/2019",
    "message_count": 374,
    "morning": "",
    "middle": "",
    "night": "",
    "high": "",
    "low": "",
    "pressure": "",
    "humidity": ""
  },
  {
    "date": "7/4/2019",
    "message_count": 401,
    "morning": "",
    "middle": "",
    "night": "",
    "high": "",
    "low": "",
    "pressure": "",
    "humidity": ""
  },
  {
    "date": "7/5/2019",
    "message_count": 258,
    "morning": "",
    "middle": "",
    "night": "",
    "high": "",
    "low": "",
    "pressure": "",
    "humidity": ""
  },
  {
    "date": "7/6/2019",
    "message_count": 419,
    "morning": "",
    "middle": "",
    "night": "",
    "high": "",
    "low": "",
    "pressure": "",
    "humidity": ""
  },
  {
    "date": "7/7/2019",
    "message_count": 8,
    "morning": "",
    "middle": "",
    "night": "",
    "high": "",
    "low": "",
    "pressure": "",
    "humidity": ""
  },
  {
    "date": "7/8/2019",
    "message_count": 0,
    "morning": "",
    "middle": "",
    "night": "",
    "high": "",
    "low": "",
    "pressure": "",
    "humidity": ""
  },
  {
    "date": "7/9/2019",
    "message_count": 0,
    "morning": "",
    "middle": "",
    "night": "",
    "high": "",
    "low": "",
    "pressure": "",
    "humidity": ""
  },
  {
    "date": "7/10/2019",
    "message_count": 0,
    "morning": "",
    "middle": "",
    "night": "",
    "high": "",
    "low": "",
    "pressure": "",
    "humidity": ""
  },
  {
    "date": "7/11/2019",
    "message_count": 0,
    "morning": "",
    "middle": "",
    "night": "",
    "high": "",
    "low": "",
    "pressure": "",
    "humidity": ""
  },
  {
    "date": "7/12/2019",
    "message_count": 0,
    "morning": "",
    "middle": "",
    "night": "",
    "high": "",
    "low": "",
    "pressure": "",
    "humidity": ""
  },
  {
    "date": "7/13/2019",
    "message_count": 0,
    "morning": "",
    "middle": "",
    "night": "",
    "high": "",
    "low": "",
    "pressure": "",
    "humidity": ""
  },
  {
    "date": "7/14/2019",
    "message_count": 0,
    "morning": "",
    "middle": "",
    "night": "",
    "high": "",
    "low": "",
    "pressure": "",
    "humidity": ""
  },
  {
    "date": "7/15/2019",
    "message_count": 0,
    "morning": "",
    "middle": "",
    "night": "",
    "high": "",
    "low": "",
    "pressure": "",
    "humidity": ""
  },
  {
    "date": "7/16/2019",
    "message_count": 1,
    "morning": "",
    "middle": "",
    "night": "",
    "high": "",
    "low": "",
    "pressure": "",
    "humidity": ""
  },
  {
    "date": "7/17/2019",
    "message_count": 0,
    "morning": "",
    "middle": "",
    "night": "",
    "high": "",
    "low": "",
    "pressure": "",
    "humidity": ""
  },
  {
    "date": "7/18/2019",
    "message_count": 0,
    "morning": "",
    "middle": "",
    "night": "",
    "high": "",
    "low": "",
    "pressure": "",
    "humidity": ""
  },
  {
    "date": "7/19/2019",
    "message_count": 0,
    "morning": "",
    "middle": "",
    "night": "",
    "high": "",
    "low": "",
    "pressure": "",
    "humidity": ""
  },
  {
    "date": "7/20/2019",
    "message_count": 0,
    "morning": "",
    "middle": "",
    "night": "",
    "high": "",
    "low": "",
    "pressure": "",
    "humidity": ""
  },
  {
    "date": "7/21/2019",
    "message_count": 0,
    "morning": "",
    "middle": "",
    "night": "",
    "high": "",
    "low": "",
    "pressure": "",
    "humidity": ""
  },
  {
    "date": "7/22/2019",
    "message_count": 0,
    "morning": "",
    "middle": "",
    "night": "",
    "high": "",
    "low": "",
    "pressure": "",
    "humidity": ""
  },
  {
    "date": "7/23/2019",
    "message_count": 0,
    "morning": "",
    "middle": "",
    "night": "",
    "high": "",
    "low": "",
    "pressure": "",
    "humidity": ""
  },
  {
    "date": "7/24/2019",
    "message_count": 216,
    "morning": "",
    "middle": "",
    "night": "",
    "high": "",
    "low": "",
    "pressure": "",
    "humidity": ""
  },
  {
    "date": "7/25/2019",
    "message_count": 510,
    "morning": "",
    "middle": "",
    "night": "",
    "high": "",
    "low": "",
    "pressure": "",
    "humidity": ""
  },
  {
    "date": "7/26/2019",
    "message_count": 524,
    "morning": "",
    "middle": "",
    "night": "",
    "high": "",
    "low": "",
    "pressure": "",
    "humidity": ""
  },
  {
    "date": "7/27/2019",
    "message_count": 534,
    "morning": "",
    "middle": "",
    "night": "",
    "high": "",
    "low": "",
    "pressure": "",
    "humidity": ""
  },
  {
    "date": "7/28/2019",
    "message_count": 53,
    "morning": "",
    "middle": "",
    "night": "",
    "high": "",
    "low": "",
    "pressure": "",
    "humidity": ""
  },
  {
    "date": "7/29/2019",
    "message_count": 0,
    "morning": "",
    "middle": "",
    "night": "",
    "high": "",
    "low": "",
    "pressure": "",
    "humidity": ""
  },
  {
    "date": "7/30/2019",
    "message_count": 152,
    "morning": "",
    "middle": "",
    "night": "",
    "high": "",
    "low": "",
    "pressure": "",
    "humidity": ""
  },
  {
    "date": "7/31/2019",
    "message_count": 436,
    "morning": "",
    "middle": "",
    "night": "",
    "high": "",
    "low": "",
    "pressure": "",
    "humidity": ""
  },
  {
    "date": "8/1/2019",
    "message_count": 60,
    "morning": "",
    "middle": "",
    "night": "",
    "high": "",
    "low": "",
    "pressure": "",
    "humidity": ""
  },
  {
    "date": "8/2/2019",
    "message_count": 218,
    "morning": "",
    "middle": "",
    "night": "",
    "high": "",
    "low": "",
    "pressure": "",
    "humidity": ""
  },
  {
    "date": "8/3/2019",
    "message_count": 393,
    "morning": "",
    "middle": "",
    "night": "",
    "high": "",
    "low": "",
    "pressure": "",
    "humidity": ""
  },
  {
    "date": "8/4/2019",
    "message_count": 76,
    "morning": "",
    "middle": "",
    "night": "",
    "high": "",
    "low": "",
    "pressure": "",
    "humidity": ""
  },
  {
    "date": "8/5/2019",
    "message_count": 506,
    "morning": "",
    "middle": "",
    "night": "",
    "high": "",
    "low": "",
    "pressure": "",
    "humidity": ""
  },
  {
    "date": "8/6/2019",
    "message_count": 375,
    "morning": "",
    "middle": "",
    "night": "",
    "high": "",
    "low": "",
    "pressure": "",
    "humidity": ""
  },
  {
    "date": "8/7/2019",
    "message_count": 239,
    "morning": "",
    "middle": "",
    "night": "",
    "high": "",
    "low": "",
    "pressure": "",
    "humidity": ""
  },
  {
    "date": "8/8/2019",
    "message_count": 344,
    "morning": "",
    "middle": "",
    "night": "",
    "high": "",
    "low": "",
    "pressure": "",
    "humidity": ""
  },
  {
    "date": "8/9/2019",
    "message_count": 96,
    "morning": "",
    "middle": "",
    "night": "",
    "high": "",
    "low": "",
    "pressure": "",
    "humidity": ""
  },
  {
    "date": "8/10/2019",
    "message_count": 329,
    "morning": "",
    "middle": "",
    "night": "",
    "high": "",
    "low": "",
    "pressure": "",
    "humidity": ""
  },
  {
    "date": "8/11/2019",
    "message_count": 598,
    "morning": "",
    "middle": "",
    "night": "",
    "high": "",
    "low": "",
    "pressure": "",
    "humidity": ""
  },
  {
    "date": "8/12/2019",
    "message_count": 427,
    "morning": "",
    "middle": "",
    "night": "",
    "high": "",
    "low": "",
    "pressure": "",
    "humidity": ""
  },
  {
    "date": "8/13/2019",
    "message_count": 399,
    "morning": "good",
    "middle": "okay-bad",
    "night": "bad",
    "high": 92.88,
    "low": 75.43,
    "pressure": 1013.39,
    "humidity": 0.84
  },
  {
    "date": "8/14/2019",
    "message_count": 216,
    "morning": "good",
    "middle": "okay-okay-good",
    "night": "good",
    "high": 91.43,
    "low": 76.39,
    "pressure": 1013.85,
    "humidity": 0.84
  },
  {
    "date": "8/15/2019",
    "message_count": 149,
    "morning": "good",
    "middle": "good",
    "night": "good",
    "high": 83.98,
    "low": 74.73,
    "pressure": 1014.91,
    "humidity": 0.92
  },
  {
    "date": "8/16/2019",
    "message_count": 422,
    "morning": "good",
    "middle": "good",
    "night": "good",
    "high": 76.68,
    "low": 71.94,
    "pressure": 1016.05,
    "humidity": 0.95
  },
  {
    "date": "8/17/2019",
    "message_count": 700,
    "morning": "good",
    "middle": "good",
    "night": "good",
    "high": 75.41,
    "low": 73.39,
    "pressure": 1017.85,
    "humidity": 0.96
  },
  {
    "date": "8/18/2019",
    "message_count": 711,
    "morning": "good",
    "middle": "good",
    "night": "good",
    "high": 80.99,
    "low": 73.38,
    "pressure": 1019.21,
    "humidity": 0.93
  },
  {
    "date": "8/19/2019",
    "message_count": 376,
    "morning": "good",
    "middle": "okay",
    "night": "okay-good",
    "high": 84.97,
    "low": 73.23,
    "pressure": 1019.15,
    "humidity": 0.88
  },
  {
    "date": "8/20/2019",
    "message_count": 388,
    "morning": "okay",
    "middle": "okay-good-good",
    "night": "good-okay-okay",
    "high": 90.72,
    "low": 72.58,
    "pressure": 1019.87,
    "humidity": 0.85
  },
  {
    "date": "8/21/2019",
    "message_count": 519,
    "morning": "okay-okay-good",
    "middle": "good",
    "night": "good",
    "high": 92.08,
    "low": 73.72,
    "pressure": 1019.34,
    "humidity": 0.79
  },
  {
    "date": "8/22/2019",
    "message_count": 310,
    "morning": "good",
    "middle": "good-okay",
    "night": "okay-bad-okay",
    "high": 92.81,
    "low": 73.1,
    "pressure": 1018.11,
    "humidity": 0.77
  },
  {
    "date": "8/23/2019",
    "message_count": 481,
    "morning": "good-good-okay",
    "middle": "okay",
    "night": "bad-bad-okay",
    "high": 92.77,
    "low": 73.52,
    "pressure": 1016.77,
    "humidity": 0.77
  },
  {
    "date": "8/24/2019",
    "message_count": 672,
    "morning": "good",
    "middle": "good",
    "night": "good",
    "high": 92.74,
    "low": 75.01,
    "pressure": 1015.37,
    "humidity": 0.78
  },
  {
    "date": "8/25/2019",
    "message_count": 556,
    "morning": "good",
    "middle": "good",
    "night": "good",
    "high": 89.27,
    "low": 73.21,
    "pressure": 1015.24,
    "humidity": 0.83
  },
  {
    "date": "8/26/2019",
    "message_count": 576,
    "morning": "good",
    "middle": "good-okay",
    "night": "okay-bad",
    "high": 91.38,
    "low": 72.73,
    "pressure": 1015.69,
    "humidity": 0.83
  },
  {
    "date": "8/27/2019",
    "message_count": 309,
    "morning": "okay",
    "middle": "okay",
    "night": "okay-bad",
    "high": 88.94,
    "low": 73.58,
    "pressure": 1015.32,
    "humidity": 0.9
  },
  {
    "date": "8/28/2019",
    "message_count": 284,
    "morning": "good",
    "middle": "good",
    "night": "good-okay-okay",
    "high": 91.06,
    "low": 74.26,
    "pressure": 1013.55,
    "humidity": 0.82
  },
  {
    "date": "8/29/2019",
    "message_count": 1091,
    "morning": "okay",
    "middle": "okay-okay-bad",
    "night": "bad",
    "high": 92.78,
    "low": 74,
    "pressure": 1014.51,
    "humidity": 0.78
  },
  {
    "date": "8/30/2019",
    "message_count": 438,
    "morning": "okay",
    "middle": "okay-good-okay",
    "night": "okay-bad",
    "high": 86.15,
    "low": 75.87,
    "pressure": 1015.97,
    "humidity": 0.87
  },
  {
    "date": "8/31/2019",
    "message_count": 132,
    "morning": "good",
    "middle": "good",
    "night": "good-okay-okay",
    "high": 90.77,
    "low": 76.64,
    "pressure": 1016.5,
    "humidity": 0.82
  },
  {
    "date": "9/1/2019",
    "message_count": 415,
    "morning": "good",
    "middle": "good",
    "night": "okay",
    "high": 85.73,
    "low": 76.57,
    "pressure": 1015.79,
    "humidity": 0.87
  },
  {
    "date": "9/2/2019",
    "message_count": 605,
    "morning": "bad-okay",
    "middle": "okay",
    "night": "okay-okay-good",
    "high": 87.54,
    "low": 76.29,
    "pressure": 1012.68,
    "humidity": 0.86
  },
  {
    "date": "9/3/2019",
    "message_count": 233,
    "morning": "good",
    "middle": "good",
    "night": "good",
    "high": 86.51,
    "low": 75.49,
    "pressure": 1011.04,
    "humidity": 0.84
  },
  {
    "date": "9/4/2019",
    "message_count": 578,
    "morning": "good",
    "middle": "good",
    "night": "okay-bad",
    "high": 86.97,
    "low": 77.33,
    "pressure": 1008.96,
    "humidity": 0.8
  },
  {
    "date": "9/5/2019",
    "message_count": 324,
    "morning": "good",
    "middle": "good",
    "night": "good",
    "high": 93.99,
    "low": 75.58,
    "pressure": 1011.47,
    "humidity": 0.71
  },
  {
    "date": "9/6/2019",
    "message_count": 651,
    "morning": "good",
    "middle": "good",
    "night": "okay",
    "high": 93.6,
    "low": 68.89,
    "pressure": 1012.2,
    "humidity": 0.71
  },
  {
    "date": "9/7/2019",
    "message_count": 863,
    "morning": "good",
    "middle": "bad-bad-okay",
    "night": "okay-okay-bad",
    "high": 94.95,
    "low": 70.45,
    "pressure": 1013.71,
    "humidity": 0.7
  },
  {
    "date": "9/8/2019",
    "message_count": 642,
    "morning": "good",
    "middle": "good-okay",
    "night": "okay",
    "high": 95.12,
    "low": 71.02,
    "pressure": 1016.21,
    "humidity": 0.73
  },
  {
    "date": "9/9/2019",
    "message_count": 412,
    "morning": "good",
    "middle": "good-okay",
    "night": "okay-bad",
    "high": 94.71,
    "low": 73.05,
    "pressure": 1019.41,
    "humidity": 0.75
  },
  {
    "date": "9/10/2019",
    "message_count": 208,
    "morning": "bad-okay",
    "middle": "okay-good-good",
    "night": "good-okay-good",
    "high": 92.8,
    "low": 71.94,
    "pressure": 1022.12,
    "humidity": 0.76
  },
  {
    "date": "9/11/2019",
    "message_count": 463,
    "morning": "okay",
    "middle": "okay-okay-good",
    "night": "good-okay-okay",
    "high": 91.7,
    "low": 72.64,
    "pressure": 1021.32,
    "humidity": 0.78
  },
  {
    "date": "9/12/2019",
    "message_count": 215,
    "morning": "good",
    "middle": "good-okay",
    "night": "okay-good-okay",
    "high": 89.81,
    "low": 74.11,
    "pressure": 1018.39,
    "humidity": 0.77
  },
  {
    "date": "9/13/2019",
    "message_count": 512,
    "morning": "good",
    "middle": "good",
    "night": "good",
    "high": "",
    "low": "",
    "pressure": "",
    "humidity": ""
  },
  {
    "date": "9/14/2019",
    "message_count": 380,
    "morning": "good",
    "middle": "okay",
    "night": "okay-bad-bad",
    "high": "",
    "low": "",
    "pressure": "",
    "humidity": ""
  },
  {
    "date": "9/15/2019",
    "message_count": 424,
    "morning": "okay",
    "middle": "good",
    "night": "good-good-okay",
    "high": "",
    "low": "",
    "pressure": "",
    "humidity": ""
  },
  {
    "date": "9/16/2019",
    "message_count": 186,
    "morning": "",
    "middle": "",
    "night": "",
    "high": "",
    "low": "",
    "pressure": "",
    "humidity": ""
  },
  {
    "date": "9/17/2019",
    "message_count": 145,
    "morning": "",
    "middle": "",
    "night": "",
    "high": "",
    "low": "",
    "pressure": "",
    "humidity": ""
  },
  {
    "date": "9/18/2019",
    "message_count": 392,
    "morning": "",
    "middle": "",
    "night": "",
    "high": "",
    "low": "",
    "pressure": "",
    "humidity": ""
  },
  {
    "date": "9/19/2019",
    "message_count": 20,
    "morning": "",
    "middle": "",
    "night": "",
    "high": "",
    "low": "",
    "pressure": "",
    "humidity": ""
  },
  {
    "date": "9/20/2019",
    "message_count": 0,
    "morning": "",
    "middle": "",
    "night": "",
    "high": "",
    "low": "",
    "pressure": "",
    "humidity": ""
  },
  {
    "date": "9/21/2019",
    "message_count": 1,
    "morning": "",
    "middle": "",
    "night": "",
    "high": "",
    "low": "",
    "pressure": "",
    "humidity": ""
  },
  {
    "date": "9/22/2019",
    "message_count": 0,
    "morning": "",
    "middle": "",
    "night": "",
    "high": "",
    "low": "",
    "pressure": "",
    "humidity": ""
  },
  {
    "date": "9/23/2019",
    "message_count": 0,
    "morning": "",
    "middle": "",
    "night": "",
    "high": "",
    "low": "",
    "pressure": "",
    "humidity": ""
  },
  {
    "date": "9/24/2019",
    "message_count": 0,
    "morning": "",
    "middle": "",
    "night": "",
    "high": "",
    "low": "",
    "pressure": "",
    "humidity": ""
  },
  {
    "date": "9/25/2019",
    "message_count": 0,
    "morning": "",
    "middle": "",
    "night": "",
    "high": "",
    "low": "",
    "pressure": "",
    "humidity": ""
  },
  {
    "date": "9/26/2019",
    "message_count": 0,
    "morning": "",
    "middle": "",
    "night": "",
    "high": "",
    "low": "",
    "pressure": "",
    "humidity": ""
  },
  {
    "date": "9/27/2019",
    "message_count": 0,
    "morning": "",
    "middle": "",
    "night": "",
    "high": "",
    "low": "",
    "pressure": "",
    "humidity": ""
  },
  {
    "date": "9/28/2019",
    "message_count": 0,
    "morning": "",
    "middle": "",
    "night": "",
    "high": "",
    "low": "",
    "pressure": "",
    "humidity": ""
  },
  {
    "date": "9/29/2019",
    "message_count": 0,
    "morning": "",
    "middle": "",
    "night": "",
    "high": "",
    "low": "",
    "pressure": "",
    "humidity": ""
  },
  {
    "date": "9/30/2019",
    "message_count": 0,
    "morning": "",
    "middle": "",
    "night": "",
    "high": "",
    "low": "",
    "pressure": "",
    "humidity": ""
  },
  {
    "date": "10/1/2019",
    "message_count": 0,
    "morning": "",
    "middle": "",
    "night": "",
    "high": "",
    "low": "",
    "pressure": "",
    "humidity": ""
  },
  {
    "date": "10/2/2019",
    "message_count": 0,
    "morning": "",
    "middle": "",
    "night": "",
    "high": "",
    "low": "",
    "pressure": "",
    "humidity": ""
  },
  {
    "date": "10/3/2019",
    "message_count": 0,
    "morning": "",
    "middle": "",
    "night": "",
    "high": "",
    "low": "",
    "pressure": "",
    "humidity": ""
  },
  {
    "date": "10/4/2019",
    "message_count": 0,
    "morning": "",
    "middle": "",
    "night": "",
    "high": "",
    "low": "",
    "pressure": "",
    "humidity": ""
  },
  {
    "date": "10/5/2019",
    "message_count": 0,
    "morning": "",
    "middle": "",
    "night": "",
    "high": "",
    "low": "",
    "pressure": "",
    "humidity": ""
  },
  {
    "date": "10/6/2019",
    "message_count": 0,
    "morning": "",
    "middle": "",
    "night": "",
    "high": "",
    "low": "",
    "pressure": "",
    "humidity": ""
  },
  {
    "date": "10/7/2019",
    "message_count": 0,
    "morning": "",
    "middle": "",
    "night": "",
    "high": "",
    "low": "",
    "pressure": "",
    "humidity": ""
  }
]
